graphene_sqlalchemy_filter/__init__.py
graphene_sqlalchemy_filter/connection_field.py
graphene_sqlalchemy_filter/filters.py
graphene_sqlalchemy_filter-1.14.0.dist-info/licenses/LICENSE
graphene_sqlalchemy_filter-1.14.0.dist-info/METADATA
graphene_sqlalchemy_filter-1.14.0.dist-info/WHEEL
graphene_sqlalchemy_filter-1.14.0.dist-info/top_level.txt
graphene_sqlalchemy_filter-1.14.0.dist-info/RECORD
