Metadata-Version: 2.4
Name: graphene-sqlalchemy-filter
Version: 1.14.0
Summary: Filters for Graphene SQLAlchemy integration
Author: Artem Fedotov
License-Expression: MIT
Project-URL: Repository, https://github.com/art1415926535/graphene-sqlalchemy-filter
Project-URL: Releasenotes, https://github.com/art1415926535/graphene-sqlalchemy-filter/releases
Project-URL: Documentation, https://github.com/art1415926535/graphene-sqlalchemy-filter/blob/master/README.md
Keywords: api,graphql,protocol,rest,relay,graphene
Classifier: Development Status :: 5 - Production/Stable
Classifier: Intended Audience :: Developers
Classifier: Operating System :: OS Independent
Classifier: Programming Language :: Python :: 3
Classifier: Programming Language :: Python :: 3.9
Classifier: Programming Language :: Python :: 3.10
Classifier: Programming Language :: Python :: 3.11
Classifier: Programming Language :: Python :: 3.12
Classifier: Programming Language :: Python :: 3.13
Classifier: Topic :: Software Development :: Libraries
Requires-Python: >=3.9
License-File: LICENSE
Requires-Dist: graphene-sqlalchemy<3,>=2.1.0
Requires-Dist: SQLAlchemy<2
Provides-Extra: dev
Requires-Dist: SQLAlchemy==1.4.45; extra == "dev"
Requires-Dist: graphene-sqlalchemy==2.3.0; extra == "dev"
Requires-Dist: SQLAlchemy-bulk-lazy-loader==0.10.0; extra == "dev"
Requires-Dist: Flask==3.1.1; extra == "dev"
Requires-Dist: Flask-GraphQL==1.4.1; extra == "dev"
Requires-Dist: tox==4.28.4; extra == "dev"
Requires-Dist: pytest==8.4.1; extra == "dev"
Requires-Dist: pytest-cov==6.2.1; extra == "dev"
Requires-Dist: coverage==7.10.1; extra == "dev"
Requires-Dist: ruff==0.12.7; extra == "dev"
Provides-Extra: ci
Requires-Dist: tox==4.28.4; extra == "ci"
Requires-Dist: coverage==7.10.1; extra == "ci"
Dynamic: license-file
